pycw/__init__.py
pycw/__main__.py
pycw/__version__.py
pycw/morse.py
pycw/synth.py
pycw-0.0.3.dist-info/LICENSE
pycw-0.0.3.dist-info/METADATA
pycw-0.0.3.dist-info/WHEEL
pycw-0.0.3.dist-info/entry_points.txt
pycw-0.0.3.dist-info/top_level.txt
pycw-0.0.3.dist-info/RECORD
