Metadata-Version: 2.1
Name: pycw
Version: 0.0.3
Summary: Generate Morse Code (CW) audio files in Python.
Home-page: https://github.com/bigsk05/pycw
Author: Ian Xia
Author-email: i@ianxia.com
License: Apache 2.0
Platform: UNKNOWN
Classifier: License :: OSI Approved :: Apache Software License
Classifier: Programming Language :: Python :: 3.4
Classifier: Programming Language :: Python :: 3.5
Classifier: Programming Language :: Python :: 3.6
Classifier: Programming Language :: Python :: 3.7
Classifier: Programming Language :: Python :: 3.8
Classifier: Programming Language :: Python :: 3.9
Classifier: Programming Language :: Python :: 3 :: Only
License-File: LICENSE
Requires-Dist: numpy
